HW_2/alu_reg.v
module alu_reg #(
parameter WIDTH = 8
)(
input clk_i,
input rst_i,
input valid_i,
input [WIDTH-1:0] first_i,
input [WIDTH-1:0] second_i,
input [1:0] opcode_i,

output reg valid_o,
output reg [WIDTH-1:0] result_o
);

reg [WIDTH-1:0] result;
reg valid;

always @(*) begin
    case(opcode_i)

        2'b00: result = first_i + second_i;

        2'b01: result = (first_i >= second_i);

        2'b10: result = second_i << first_i;

        2'b11: result = ~(first_i | second_i);
        endcase
end

always @(posedge clk_i) begin

    valid <= valid_i;

    if ((opcode_i == 2'b00) && (((first_i >> (WIDTH - 1)) == (second_i >> (WIDTH - 1))) && (result >> (WIDTH - 1)) != (first_i >> (WIDTH - 1)))) begin

        valid <= 1'b0;

    end

    if (rst_i) begin

        valid <= 1'b0;

    end else if (valid_i) begin

        result_o <= result;

    end

    valid_o <= valid;
end
endmodule

HW_2/alu_reg_tb.v
`timescale 1ns/1ps
module alu_reg_tb();

localparam TEST_WIDTH = 3;

reg clk_i;
reg rst_i;
reg valid_i;
reg [TEST_WIDTH-1:0] first_i;
reg [TEST_WIDTH-1:0] second_i;
reg [1:0] opcode_i;

wire valid_o;
wire [TEST_WIDTH-1:0] result_o;

alu_reg #(
.WIDTH(TEST_WIDTH)
) malu_reg_inst (
.clk_i (clk_i),
.rst_i (rst_i),
.valid_i (valid_i),
.first_i (first_i),
.second_i(second_i),
.opcode_i(opcode_i),
.valid_o(valid_o),
.result_o(result_o)
);

always begin
    clk_i = 1'b0; #1;
    clk_i = 1'b1; #1;
    end

initial begin
    $dumpvars;

    //test reset
    @(posedge clk_i); #0.5; //enable reset
    rst_i = 1'b1;
    #3;

    @(posedge clk_i); #0.5; //disable reset
    rst_i = 1'b0;
    #3;

    //test of correct addition
    first_i = 3'b001;
    second_i = 3'b001;
    valid_i = 1'b1;
    opcode_i = 2'b00;

    @(posedge clk_i); #1; // 001 + 001 = 010 (1 + 1 = 2)
    rst_i = 1'b1; //reset
    #1;
    rst_i = 1'b0;
    #1;

    first_i = 3'b111;
    second_i = 3'b111;
    valid_i = 1'b1;
    opcode_i = 2'b00;

    @(posedge clk_i); #1; // 111 + 111 = 110 (-1 - 1 = -2)
    rst_i = 1'b1; //reset
    #1;
    rst_i = 1'b0;
    #1;

    //test of overflow addition
    first_i = 3'b011;
    second_i = 3'b011;
    valid_i = 1'b1;
    opcode_i = 2'b00;

    @(posedge clk_i); #1; // 011 + 011 = 111, valid_o should be 0
    rst_i = 1'b1; //reset
    #1;
    rst_i = 1'b0;
    #1;

    //test of second_i <= first_i
    first_i = 3'b011;
    second_i = 3'b011;
    valid_i = 1'b1;
    opcode_i = 2'b01;

    @(posedge clk_i); #1; // 011 <= 011 result_o = 1
    rst_i = 1'b1; //reset
    #1;
    rst_i = 1'b0;
    #1;

    first_i = 3'b011;
    second_i = 3'b101;
    valid_i = 1'b1;
    opcode_i = 2'b01;

    @(posedge clk_i); #1; // 101 > 011 result_o = 0
    rst_i = 1'b1; //reset
    #1;
    rst_i = 1'b0;
    #1;

    first_i = 3'b011;
    second_i = 3'b001;
    valid_i = 1'b1;
    opcode_i = 2'b01;

    @(posedge clk_i); #1; // 001 <= 011 result_o = 1
    rst_i = 1'b1; //reset
    #1;
    rst_i = 1'b0;
    #1;

    //test of logical shift
    first_i = 3'b010;
    second_i = 3'b001;
    valid_i = 1'b1;
    opcode_i = 2'b10;

    @(posedge clk_i); #1; // 001 << 2 result_o = 100
    rst_i = 1'b1; //reset
    #1;
    rst_i = 1'b0;
    #1;

    first_i = 3'b100;
    second_i = 3'b001;
    valid_i = 1'b1;
    opcode_i = 2'b10;

    @(posedge clk_i); #1; // 001 << 4 result_o = 000
    rst_i = 1'b1; //reset
    #1;
    rst_i = 1'b0;
    #1;
    
    //test of NOR
    first_i = 3'b101;
    second_i = 3'b101;
    valid_i = 1'b1;
    opcode_i = 2'b11;

    @(posedge clk_i); #1; // ~(101 & 101) result_o = 010
    rst_i = 1'b1; //reset
    #1;
    rst_i = 1'b0;
    #1;

    $finish;
end
endmodule

HW_2/dump.vcd
$date
	Tue Mar 25 20:34:47 2025
$end
$version
	Icarus Verilog
$end
$timescale
	1ps
$end
$scope module alu_reg_tb $end
$var wire 1 ! valid_o $end
$var wire 3 " result_o [2:0] $end
$var parameter 32 # TEST_WIDTH $end
$var reg 1 $ clk_i $end
$var reg 3 % first_i [2:0] $end
$var reg 2 & opcode_i [1:0] $end
$var reg 1 ' rst_i $end
$var reg 3 ( second_i [2:0] $end
$var reg 1 ) valid_i $end
$scope module malu_reg_inst $end
$var wire 1 $ clk_i $end
$var wire 3 * first_i [2:0] $end
$var wire 2 + opcode_i [1:0] $end
$var wire 1 ' rst_i $end
$var wire 3 , second_i [2:0] $end
$var wire 1 ) valid_i $end
$var parameter 32 - WIDTH $end
$var reg 3 . result [2:0] $end
$var reg 3 / result_o [2:0] $end
$var reg 1 0 valid $end
$var reg 1 ! valid_o $end
$upscope $end
$upscope $end
$enddefinitions $end
$comment Show the parameter values. $end
$dumpall
b11 -
b11 #
$end
#0
$dumpvars
x0
bx /
bx .
bx ,
bx +
bx *
x)
bx (
x'
bx &
bx %
0$
bx "
x!
$end
#1000
1$
#1500
1'
#2000
0$
#3000
00
1$
#4000
0$
#5000
0!
00
1$
#5500
0'
#6000
0$
#7000
x0
1$
#8000
0$
#8500
b10 .
b0 &
b0 +
1)
b1 (
b1 ,
b1 %
b1 *
#9000
x!
b10 "
b10 /
10
1$
#10000
1'
0$
#11000
1!
0'
1$
#12000
b110 .
b111 (
b111 ,
b111 %
b111 *
0$
#13000
b110 "
b110 /
1$
#14000
1'
0$
#15000
0'
1$
#16000
b11 (
b11 ,
b11 %
b11 *
0$
#17000
00
1$
#18000
1'
0$
#19000
0!
00
0'
1$
#20000
b1 .
b1 &
b1 +
0$
#21000
b1 "
b1 /
10
1$
#22000
1'
0$
#23000
1!
0'
1$
#24000
b0 .
b101 (
b101 ,
0$
#25000
b0 "
b0 /
1$
#26000
1'
0$
#27000
0'
1$
#28000
b1 .
b1 (
b1 ,
0$
#29000
b1 "
b1 /
1$
#30000
1'
0$
#31000
0'
1$
#32000
b100 .
b10 &
b10 +
b10 %
b10 *
0$
#33000
b100 "
b100 /
1$
#34000
1'
0$
#35000
0'
1$
#36000
b0 .
b100 %
b100 *
0$
#37000
b0 "
b0 /
1$
#38000
1'
0$
#39000
0'
1$
#40000
b10 .
b11 &
b11 +
b101 (
b101 ,
b101 %
b101 *
0$
#41000
b10 "
b10 /
1$
#42000
1'
0$
#43000
0'
1$
